goodwe/__init__.py
goodwe/const.py
goodwe/dt.py
goodwe/es.py
goodwe/et.py
goodwe/exceptions.py
goodwe/inverter.py
goodwe/modbus.py
goodwe/model.py
goodwe/protocol.py
goodwe/sensor.py
goodwe-0.4.8.dist-info/LICENSE
goodwe-0.4.8.dist-info/METADATA
goodwe-0.4.8.dist-info/WHEEL
goodwe-0.4.8.dist-info/top_level.txt
goodwe-0.4.8.dist-info/RECORD
