Metadata-Version: 2.1
Name: goodwe
Version: 0.4.8
Summary: Read data from GoodWe inverter via local network
Home-page: https://github.com/marcelblijleven/goodwe
Author: Martin Letenay, Marcel Blijleven
Author-email: 'marcelblijleven@gmail.com
License: MIT
Keywords: GoodWe,Solar Panel,Inverter,Photovoltaics,PV
Classifier: Development Status :: 5 - Production/Stable
Classifier: Intended Audience :: Developers
Classifier: Topic :: Software Development :: Libraries :: Python Modules
Classifier: License :: OSI Approved :: MIT License
Classifier: Programming Language :: Python :: 3
Classifier: Programming Language :: Python :: 3.8
Classifier: Programming Language :: Python :: 3.9
Classifier: Programming Language :: Python :: 3.10
Classifier: Programming Language :: Python :: 3.11
Classifier: Programming Language :: Python :: 3.12
Classifier: Programming Language :: Python :: 3.13
Requires-Python: >=3.8
License-File: LICENSE
